async_cache_ext-1.1.1.dist-info/licenses/LICENSE
cache/__init__.py
cache/async_lru.py
cache/async_ttl.py
cache/key.py
cache/lru.py
cache/stats.py
cache/types.py
tests/__init__.py
tests/lru_test.py
tests/ttl_test.py
async_cache_ext-1.1.1.dist-info/METADATA
async_cache_ext-1.1.1.dist-info/WHEEL
async_cache_ext-1.1.1.dist-info/top_level.txt
async_cache_ext-1.1.1.dist-info/RECORD
