Metadata-Version: 2.4
Name: async-cache-ext
Version: 1.1.1
Summary: A high-performance async caching solution for Python with extended features
Home-page: https://github.com/doubledare704/async-cache
Author: doubledare704
Author-email: doubledare704 <doubledare704@github.com>
License: MIT
Project-URL: Homepage, https://github.com/doubledare704/async-cache
Project-URL: Repository, https://github.com/doubledare704/async-cache
Project-URL: Issues, https://github.com/doubledare704/async-cache/issues
Keywords: asyncio,lru,cache,async,cache,lru-cache,ttl
Classifier: Programming Language :: Python :: 3.9
Classifier: Programming Language :: Python :: 3.10
Classifier: Programming Language :: Python :: 3.11
Classifier: Programming Language :: Python :: 3.12
Classifier: License :: OSI Approved :: MIT License
Classifier: Operating System :: OS Independent
Classifier: Framework :: AsyncIO
Classifier: Intended Audience :: Developers
Classifier: Topic :: Software Development :: Libraries :: Python Modules
Requires-Python: >=3.9
License-File: LICENSE
Dynamic: author
Dynamic: home-page
Dynamic: license-file
Dynamic: requires-python
